Metadata-Version: 2.1
Name: spolstore
Version: 0.9
Summary: rdflib store using SQLite Fulltext index
Home-page: https://github.com/epoz/spolstore
Author: epoz
Author-email: ep@epoz.org
License: BSD-3-Clause
Project-URL: Documentation, https://github.com/epoz/spolstore/blob/main/README.md
Project-URL: Source, https://github.com/epoz/spolstore
Project-URL: Tracker, https://github.com/epoz/spolstore/issues
Platform: any
Classifier: Programming Language :: Python
Classifier: Programming Language :: Python :: 3 :: Only
Classifier: Programming Language :: Python :: 3.7
Classifier: Programming Language :: Python :: 3.8
Classifier: Programming Language :: Python :: 3.9
Classifier: Programming Language :: Python :: 3.10
Classifier: License :: OSI Approved :: BSD License
Classifier: Topic :: Software Development :: Libraries :: Python Modules
Classifier: Topic :: Database :: Database Engines/Servers
Requires-Python: >=3.7
License-File: LICENSE
